MBAR_PyTorch/MBAR.py
MBAR_PyTorch/__init__.py
MBAR_PyTorch-0.0.0a1.dist-info/DESCRIPTION.rst
MBAR_PyTorch-0.0.0a1.dist-info/METADATA
MBAR_PyTorch-0.0.0a1.dist-info/RECORD
MBAR_PyTorch-0.0.0a1.dist-info/WHEEL
MBAR_PyTorch-0.0.0a1.dist-info/metadata.json
MBAR_PyTorch-0.0.0a1.dist-info/top_level.txt
