Metadata-Version: 2.0
Name: MBAR-PyTorch
Version: 0.0.0a1
Summary: A fast implementation of MBAR method using PyTorch
Home-page: https://github.com/xqding/MBAR_PyTorch
Author: Xinqiang (Shawn) Ding
Author-email: xqding@umich.edu
License: MIT
Platform: UNKNOWN
Classifier: Programming Language :: Python :: 3
Classifier: License :: OSI Approved :: MIT License
Classifier: Operating System :: OS Independent
Requires-Dist: numpy (>=1.14.0)
Requires-Dist: scipy (>=1.1.0)
Requires-Dist: torch (>=0.4.0)
